{
  "generatedAt": "2026-03-07T14:50:23.806Z",
  "vsCurrencies": [
    "usd",
    "jpy"
  ],
  "chains": {
    "btc": {
      "label": "Bitcoin",
      "feeUSD": 2.0400300000000002,
      "feeJPY": 321.88620000000003,
      "speedSec": 600,
      "status": "normal",
      "updated": "2026-03-07T14:50:23.806Z",
      "native": {
        "amount": 0.00003,
        "symbol": "BTC"
      },
      "source": {
        "price": {
          "provider": "coingecko-demo",
          "id": "bitcoin"
        }
      }
    },
    "eth": {
      "label": "Ethereum",
      "feeUSD": 0.6253065000000001,
      "feeJPY": 98.66398500000003,
      "speedSec": 30,
      "status": "normal",
      "updated": "2026-03-07T14:50:23.806Z",
      "native": {
        "amount": 0.00031500000000000007,
        "symbol": "ETH"
      },
      "source": {
        "price": {
          "provider": "coingecko-demo",
          "id": "ethereum"
        }
      }
    },
    "bsc": {
      "label": "BNB Smart Chain",
      "feeUSD": 0.0658392,
      "feeJPY": 10.388385000000001,
      "speedSec": 5,
      "status": "fast",
      "updated": "2026-03-07T14:50:23.806Z",
      "native": {
        "amount": 0.000105,
        "symbol": "BNB"
      },
      "source": {
        "price": {
          "provider": "coingecko-demo",
          "id": "binancecoin"
        }
      }
    },
    "sol": {
      "label": "Solana",
      "feeUSD": 0.00042100000000000004,
      "feeJPY": 0.06642505000000001,
      "speedSec": 10,
      "status": "fast",
      "updated": "2026-03-07T14:50:23.806Z",
      "native": {
        "amount": 0.000005,
        "symbol": "SOL"
      },
      "source": {
        "price": {
          "provider": "coingecko-demo",
          "id": "solana"
        }
      }
    },
    "tron": {
      "label": "Tron",
      "feeUSD": 0.0284473,
      "feeJPY": 4.489,
      "speedSec": 5,
      "status": "fast",
      "updated": "2026-03-07T14:50:23.806Z",
      "native": {
        "amount": 0.1,
        "symbol": "TRX"
      },
      "source": {
        "price": {
          "provider": "coingecko-demo",
          "id": "tron"
        }
      }
    },
    "avax": {
      "label": "Avalanche C-Chain",
      "feeUSD": 0.009000000000000001,
      "feeJPY": 1.41961,
      "speedSec": 15,
      "status": "fast",
      "updated": "2026-03-07T14:50:23.806Z",
      "native": {
        "amount": 0.001,
        "symbol": "AVAX"
      },
      "source": {
        "price": {
          "provider": "coingecko-demo",
          "id": "avalanche-2"
        }
      }
    },
    "xrp": {
      "label": "XRP Ledger",
      "feeUSD": 0.000013600000000000002,
      "feeJPY": 0.0021531000000000002,
      "speedSec": 5,
      "status": "fast",
      "updated": "2026-03-07T14:50:23.806Z",
      "native": {
        "amount": 0.00001,
        "symbol": "XRP"
      },
      "source": {
        "price": {
          "provider": "coingecko-demo",
          "id": "ripple"
        }
      }
    },
    "arbitrum": {
      "label": "Arbitrum One",
      "feeUSD": 0.009812500000000002,
      "feeJPY": 1.548,
      "speedSec": 15,
      "status": "fast",
      "updated": "2026-03-07T14:50:23.806Z",
      "native": {
        "amount": 0.1,
        "symbol": "ARB"
      },
      "source": {
        "price": {
          "provider": "coingecko-demo",
          "id": "arbitrum"
        }
      }
    },
    "optimism": {
      "label": "Optimism",
      "feeUSD": 0.0118384,
      "feeJPY": 1.868,
      "speedSec": 15,
      "status": "fast",
      "updated": "2026-03-07T14:50:23.806Z",
      "native": {
        "amount": 0.1,
        "symbol": "OP"
      },
      "source": {
        "price": {
          "provider": "coingecko-demo",
          "id": "optimism"
        }
      }
    }
  }
}
