{
  "generatedAt": "2026-01-15T16:01:28.610Z",
  "vsCurrencies": [
    "usd",
    "jpy"
  ],
  "chains": {
    "btc": {
      "label": "Bitcoin",
      "feeUSD": 2.89974,
      "feeJPY": 459.72387000000003,
      "speedSec": 600,
      "status": "normal",
      "updated": "2026-01-15T16:01:28.610Z",
      "native": {
        "amount": 0.00003,
        "symbol": "BTC"
      },
      "source": {
        "price": {
          "provider": "coingecko-demo",
          "id": "bitcoin"
        }
      }
    },
    "eth": {
      "label": "Ethereum",
      "feeUSD": 1.0467261000000003,
      "feeJPY": 165.94735500000004,
      "speedSec": 30,
      "status": "normal",
      "updated": "2026-01-15T16:01:28.610Z",
      "native": {
        "amount": 0.00031500000000000007,
        "symbol": "ETH"
      },
      "source": {
        "price": {
          "provider": "coingecko-demo",
          "id": "ethereum"
        }
      }
    },
    "bsc": {
      "label": "BNB Smart Chain",
      "feeUSD": 0.09837135000000001,
      "feeJPY": 15.595755,
      "speedSec": 5,
      "status": "fast",
      "updated": "2026-01-15T16:01:28.610Z",
      "native": {
        "amount": 0.000105,
        "symbol": "BNB"
      },
      "source": {
        "price": {
          "provider": "coingecko-demo",
          "id": "binancecoin"
        }
      }
    },
    "sol": {
      "label": "Solana",
      "feeUSD": 0.0007132500000000001,
      "feeJPY": 0.11307500000000001,
      "speedSec": 10,
      "status": "fast",
      "updated": "2026-01-15T16:01:28.610Z",
      "native": {
        "amount": 0.000005,
        "symbol": "SOL"
      },
      "source": {
        "price": {
          "provider": "coingecko-demo",
          "id": "solana"
        }
      }
    },
    "tron": {
      "label": "Tron",
      "feeUSD": 0.030757000000000003,
      "feeJPY": 4.876,
      "speedSec": 5,
      "status": "fast",
      "updated": "2026-01-15T16:01:28.610Z",
      "native": {
        "amount": 0.1,
        "symbol": "TRX"
      },
      "source": {
        "price": {
          "provider": "coingecko-demo",
          "id": "tron"
        }
      }
    },
    "avax": {
      "label": "Avalanche C-Chain",
      "feeUSD": 0.013949999999999999,
      "feeJPY": 2.21206,
      "speedSec": 15,
      "status": "fast",
      "updated": "2026-01-15T16:01:28.610Z",
      "native": {
        "amount": 0.001,
        "symbol": "AVAX"
      },
      "source": {
        "price": {
          "provider": "coingecko-demo",
          "id": "avalanche-2"
        }
      }
    },
    "xrp": {
      "label": "XRP Ledger",
      "feeUSD": 0.0000209,
      "feeJPY": 0.0033060000000000003,
      "speedSec": 5,
      "status": "fast",
      "updated": "2026-01-15T16:01:28.610Z",
      "native": {
        "amount": 0.00001,
        "symbol": "XRP"
      },
      "source": {
        "price": {
          "provider": "coingecko-demo",
          "id": "ripple"
        }
      }
    },
    "arbitrum": {
      "label": "Arbitrum One",
      "feeUSD": 0.0209299,
      "feeJPY": 3.318,
      "speedSec": 15,
      "status": "fast",
      "updated": "2026-01-15T16:01:28.610Z",
      "native": {
        "amount": 0.1,
        "symbol": "ARB"
      },
      "source": {
        "price": {
          "provider": "coingecko-demo",
          "id": "arbitrum"
        }
      }
    },
    "optimism": {
      "label": "Optimism",
      "feeUSD": 0.0342761,
      "feeJPY": 5.434000000000001,
      "speedSec": 15,
      "status": "fast",
      "updated": "2026-01-15T16:01:28.610Z",
      "native": {
        "amount": 0.1,
        "symbol": "OP"
      },
      "source": {
        "price": {
          "provider": "coingecko-demo",
          "id": "optimism"
        }
      }
    }
  }
}
